epayco_django/__init__.py
epayco_django/admin.py
epayco_django/models.py
epayco_django/settings.py
epayco_django/signals.py
epayco_django/tests.py
epayco_django/urls.py
epayco_django/utils.py
epayco_django/views.py
epayco_django/migrations/0001_initial.py
epayco_django/migrations/0002_transaction_id_max_length.py
epayco_django/migrations/0003_extend_response_reason_text_length.py
epayco_django/migrations/0004_add_length_to_transaction_fields.py
epayco_django/migrations/0005_extends_document_number_length.py
epayco_django/migrations/__init__.py
epayco_django/templates/epayco_web_checkout_button.html
epayco_django/templates/simple_payment_response.html
epayco_django/templatetags/__init__.py
epayco_django/templatetags/epayco_checkout.py
epayco_django-0.1.0.dist-info/LICENSE
epayco_django-0.1.0.dist-info/METADATA
epayco_django-0.1.0.dist-info/WHEEL
epayco_django-0.1.0.dist-info/top_level.txt
epayco_django-0.1.0.dist-info/RECORD
